spys1proxy/__init__.py
spys1proxy/main.py
spys1proxy-0.0.2.dist-info/LICENSE.txt
spys1proxy-0.0.2.dist-info/METADATA
spys1proxy-0.0.2.dist-info/WHEEL
spys1proxy-0.0.2.dist-info/top_level.txt
spys1proxy-0.0.2.dist-info/RECORD
