Metadata-Version: 2.1
Name: spys1proxy
Version: 0.0.2
Summary: Get proxy list from http://spys.one/free-proxy-list/
Home-page: https://github.com/doubledare704/spys_one_proxy.git
Author: Oleksii Ovdiienko
Author-email: doubledare704@gmail.com
License: MIT
Download-URL: https://pypi.org/project/spys1proxy/0.0.1/
Keywords: Proxy,FreeProxy
Platform: UNKNOWN
Requires-Python: >=3.7
Requires-Dist: pyppeteer (~=0.2.2)
